<?xml version="1.0" encoding="utf-8" standalone="yes"?>
<!DOCTYPE ROOT PUBLIC "" ""[]>
<PresetModel xmlns:r="reflection" r:Version="2">
  <ChannelValues>
    <Item Key="Blend.Blend Modulation.Chebyshev Distance">
      <Value r:Type="Float32 [Primitive]">0</Value>
    </Item>
    <Item Key="Blend.Blend Modulation.Depth B">
      <Value r:Type="Float32 [Primitive]">0</Value>
    </Item>
    <Item Key="Blend.Blend Modulation.Deptha A">
      <Value r:Type="Float32 [Primitive]">0</Value>
    </Item>
    <Item Key="Blend.Blend Modulation.Euclidian Distance">
      <Value r:Type="Float32 [Primitive]">1</Value>
    </Item>
    <Item Key="Blend.Blend Modulation.FFT">
      <Value r:Type="Float32 [Primitive]">0</Value>
    </Item>
    <Item Key="Blend.Blend Modulation.Lighting">
      <Value r:Type="Float32 [Primitive]">0</Value>
    </Item>
    <Item Key="Blend.Blend Modulation.Manhattan Distance">
      <Value r:Type="Float32 [Primitive]">0</Value>
    </Item>
    <Item Key="Blend.Blend Modulation.Noise Amp">
      <Value r:Type="Float32 [Primitive]">0</Value>
    </Item>
    <Item Key="Blend.Blend Modulation.Noise Freq">
      <Value r:Type="Float32 [Primitive]">0.06</Value>
    </Item>
    <Item Key="Blend.Blend Modulation.Noise Speed">
      <Value r:Type="Float32 [Primitive]">0.27</Value>
    </Item>
    <Item Key="Blend.Blend Modulation.Smoothness">
      <Value r:Type="Float32 [Primitive]">0.3</Value>
    </Item>
    <Item Key="Blend.Blend Modulation.Texture Noise">
      <Value r:Type="Float32 [Primitive]">0.1</Value>
    </Item>
    <Item Key="Blend.Blend Modulation.Tracking">
      <Value r:Type="Float32 [Primitive]">0</Value>
    </Item>
    <Item Key="Blend.Blend Modulation.X">
      <Value r:Type="Float32 [Primitive]">0</Value>
    </Item>
    <Item Key="Blend.Blend Modulation.Y">
      <Value r:Type="Float32 [Primitive]">0</Value>
    </Item>
    <Item Key="Blend.Blend Modulation.z">
      <Value r:Type="Float32 [Primitive]">0</Value>
    </Item>
  </ChannelValues>
</PresetModel>